AUTHORS
CHANGELOG.rst
LICENSE
MANIFEST.in
README.rst
setup.py
dynamic_password/__init__.py
dynamic_password/backends.py
dynamic_password/models.py
dynamic_password/tests.py
dynamic_password/utils.py
dynamic_password/views.py
dynamic_password.egg-info/PKG-INFO
dynamic_password.egg-info/SOURCES.txt
dynamic_password.egg-info/dependency_links.txt
dynamic_password.egg-info/namespace_packages.txt
dynamic_password.egg-info/not-zip-safe
dynamic_password.egg-info/requires.txt
dynamic_password.egg-info/top_level.txt