Metadata-Version: 1.0
Name: dynamic-password
Version: 0.0.2
Summary: Add dynamic password authentication to your web service
Home-page: https://bitbucket.org/DNX/django-dynamic-password/
Author: Denis Darii
Author-email: denis.darii@gmail.com
License: BSD License
Download-URL: http://bitbucket.org/DNX/django-dynamic-password/downloads
Keywords: dynamic password authentication
Platform: UNKNOWN
Classifier: Development Status :: 3 - Alpha
Classifier: Framework :: Django
Classifier: Intended Audience :: Developers
Classifier: Intended Audience :: System Administrators
Classifier: Programming Language :: Python
